git_stacktrace_java/__init__.py
git_stacktrace_java/api.py
git_stacktrace_java/cmd.py
git_stacktrace_java/git.py
git_stacktrace_java/parse_trace.py
git_stacktrace_java/result.py
git_stacktrace_java/server.py
git_stacktrace_java-0.1.3.dist-info/METADATA
git_stacktrace_java-0.1.3.dist-info/WHEEL
git_stacktrace_java-0.1.3.dist-info/entry_points.txt
git_stacktrace_java-0.1.3.dist-info/licenses/AUTHORS
git_stacktrace_java-0.1.3.dist-info/licenses/LICENSE
git_stacktrace_java-0.1.3.dist-info/RECORD
